fhadmin/__init__.py
fhadmin/apps.py
fhadmin/models.py
fhadmin/locale/de/LC_MESSAGES/django.mo
fhadmin/locale/de/LC_MESSAGES/django.po
fhadmin/static/fhadmin/fhadmin.css
fhadmin/static/fhadmin/fhadmin.js
fhadmin/templates/admin/base_site.html
fhadmin/templates/admin/group_list.html
fhadmin/templates/admin/index.html
fhadmin/templatetags/__init__.py
fhadmin/templatetags/fhadmin_groups.py
django_fhadmin-2.3.1.dist-info/LICENSE
django_fhadmin-2.3.1.dist-info/METADATA
django_fhadmin-2.3.1.dist-info/WHEEL
django_fhadmin-2.3.1.dist-info/top_level.txt
django_fhadmin-2.3.1.dist-info/RECORD
