Metadata-Version: 2.1
Name: django_fhadmin
Version: 2.3.1
Summary: Modifies the stock Django-Administration interface to fit our ideas a little bit better.
Home-page: http://github.com/feinheit/django-fhadmin/
Author: Matthias Kestenholz
Author-email: mk@feinheit.ch
License: BSD-3-Clause
Platform: OS Independent
Classifier: License :: OSI Approved :: BSD License
Classifier: Programming Language :: Python :: 3
Classifier: Programming Language :: Python :: 3 :: Only
Classifier: Programming Language :: Python :: 3.10
Classifier: Programming Language :: Python :: 3.11
Classifier: Programming Language :: Python :: 3.12
Requires-Python: >=3.10
License-File: LICENSE
Requires-Dist: Django >=3.2
Provides-Extra: tests
Requires-Dist: coverage ; extra == 'tests'
